pukiWikiDumper/__init__.py
pukiWikiDumper/__main__.py
pukiWikiDumper/__version__.py
pukiWikiDumper/dump/content/content.py
pukiWikiDumper/dump/content/revisions.py
pukiWikiDumper/dump/content/titles.py
pukiWikiDumper/dump/dokuDumper.py
pukiWikiDumper/dump/info/__init__.py
pukiWikiDumper/dump/info/info.py
pukiWikiDumper/dump/media/__init__.py
pukiWikiDumper/dump/media/media.py
pukiWikiDumper/exceptions.py
pukiWikiDumper/utils/config.py
pukiWikiDumper/utils/delay.py
pukiWikiDumper/utils/dump_lock.py
pukiWikiDumper/utils/ia_checker.py
pukiWikiDumper/utils/patch.py
pukiWikiDumper/utils/session.py
pukiWikiDumper/utils/util.py
pukiWikiUploader/__init__.py
pukiWikiUploader/__main__.py
pukiWikiUploader/__version__.py
pukiWikiUploader/uploader.py
pukiwikidumper-0.0.19.dist-info/LICENSE
pukiwikidumper-0.0.19.dist-info/METADATA
pukiwikidumper-0.0.19.dist-info/WHEEL
pukiwikidumper-0.0.19.dist-info/entry_points.txt
pukiwikidumper-0.0.19.dist-info/RECORD
